AUTHORS.rst
CONTRIBUTING.rst
HISTORY.rst
LICENSE
MANIFEST.in
README.rst
setup.cfg
setup.py
docs/Makefile
docs/authors.rst
docs/conf.py
docs/contributing.rst
docs/history.rst
docs/index.rst
docs/installation.rst
docs/make.bat
docs/readme.rst
docs/usage.rst
pyhydro/__init__.py
pyhydro/cli.py
pyhydro/pyhydro.py
pyhydro.egg-info/PKG-INFO
pyhydro.egg-info/SOURCES.txt
pyhydro.egg-info/dependency_links.txt
pyhydro.egg-info/entry_points.txt
pyhydro.egg-info/not-zip-safe
pyhydro.egg-info/requires.txt
pyhydro.egg-info/top_level.txt
tests/__init__.py
tests/test_pyhydro.py