Metadata-Version: 1.2
Name: pyhydro
Version: 0.1.0
Summary: A Python package for modeling fill-spill hydrology in depression-dominated landscapes
Home-page: https://github.com/giswqs/pyhydro
Author: Qiusheng Wu
Author-email: giswqs@gmail.com
License: MIT license
Keywords: pyhydro
Platform: UNKNOWN
Classifier: Development Status :: 2 - Pre-Alpha
Classifier: Intended Audience :: Developers
Classifier: License :: OSI Approved :: MIT License
Classifier: Natural Language :: English
Classifier: Programming Language :: Python :: 2
Classifier: Programming Language :: Python :: 2.7
Classifier: Programming Language :: Python :: 3
Classifier: Programming Language :: Python :: 3.5
Classifier: Programming Language :: Python :: 3.6
Classifier: Programming Language :: Python :: 3.7
Classifier: Programming Language :: Python :: 3.8
Requires-Python: >=2.7, !=3.0.*, !=3.1.*, !=3.2.*, !=3.3.*, !=3.4.*
